python_bytecode_ir.py
python_bytecode_ir-0.1.0a0.dist-info/licenses/LICENSE
python_bytecode_ir-0.1.0a0.dist-info/METADATA
python_bytecode_ir-0.1.0a0.dist-info/WHEEL
python_bytecode_ir-0.1.0a0.dist-info/top_level.txt
python_bytecode_ir-0.1.0a0.dist-info/RECORD
