Metadata-Version: 2.4
Name: python-bytecode-ir
Version: 0.1.0a0
Summary: An expressive set of Python classes modeling Python bytecode as an SSA-form IR.
Author-email: Jifeng Wu <jifengwu2k@gmail.com>
License-Expression: MIT
Project-URL: Homepage, https://github.com/jifengwu2k/python-bytecode-ir
Project-URL: Bug Tracker, https://github.com/jifengwu2k/python-bytecode-ir/issues
Classifier: Programming Language :: Python :: 2
Classifier: Programming Language :: Python :: 3
Classifier: Operating System :: OS Independent
Requires-Python: >=2
License-File: LICENSE
Requires-Dist: enum34; python_version < "3.4"
Dynamic: license-file
